[
  {
    "id": 1,
    "icon": "passport",
    "label": "تجديد جواز السفر",
    "desc": "تجديد وثيقة السفر الأردنية عبر السفارات والقنصليات",
    "color": "#1B5E3B",
    "steps": 4,
    "fee": "50 د.أ"
  },
  {
    "id": 2,
    "icon": "file-document-multiple-outline",
    "label": "توثيق الوثائق",
    "desc": "تصديق الأوراق والمستندات الرسمية خارج الأردن",
    "color": "#1565C0",
    "steps": 3,
    "fee": "10-30 د.أ"
  },
  {
    "id": 3,
    "icon": "baby-carriage",
    "label": "تسجيل المولود",
    "desc": "تسجيل المواليد الأردنيين خارج المملكة",
    "color": "#6A1B9A",
    "steps": 5,
    "fee": "مجاناً"
  },
  {
    "id": 4,
    "icon": "ring",
    "label": "توثيق عقد زواج",
    "desc": "توثيق عقود الزواج المُبرمة خارج المملكة",
    "color": "#AD1457",
    "steps": 4,
    "fee": "25 د.أ"
  },
  {
    "id": 5,
    "icon": "account-convert",
    "label": "نقل الكفالة وشؤون العمالة",
    "desc": "خدمات نقل الكفالة وتعديل أوضاع العمالة الأردنية",
    "color": "#BF360C",
    "steps": 6,
    "fee": "حسب الدولة"
  },
  {
    "id": 6,
    "icon": "bank",
    "label": "الشؤون القنصلية",
    "desc": "استفسارات وخدمات قنصلية متنوعة للمغتربين",
    "color": "#006064",
    "steps": 2,
    "fee": "متغيرة"
  }
]
